joshbasiccalculator/__init__.py
DigiCalculator-0.0.1.dist-info/LICENCE.txt
DigiCalculator-0.0.1.dist-info/METADATA
DigiCalculator-0.0.1.dist-info/WHEEL
DigiCalculator-0.0.1.dist-info/top_level.txt
DigiCalculator-0.0.1.dist-info/RECORD
